mcp_chain/__init__.py
mcp_chain/__main__.py
mcp_chain/builder.py
mcp_chain/cli.py
mcp_chain/cli_mcp.py
mcp_chain/external.py
mcp_chain/fastmcp.py
mcp_chain/middleware.py
mcp_chain/py.typed
mcp_chain/serve.py
mcp_chain/types.py
mcp_chain-0.1.9.dist-info/METADATA
mcp_chain-0.1.9.dist-info/WHEEL
mcp_chain-0.1.9.dist-info/entry_points.txt
mcp_chain-0.1.9.dist-info/licenses/LICENSE
mcp_chain-0.1.9.dist-info/RECORD
