Metadata-Version: 2.4
Name: mcp-chain
Version: 0.1.9
Summary: An MCP server proxy with to modify and enrich calls to other MCP servers
Author-email: Ronie Uliana <ronie.uliana@gmail.com>
License: MIT License
License-File: LICENSE
Classifier: Development Status :: 3 - Alpha
Classifier: Intended Audience :: Developers
Classifier: License :: OSI Approved :: MIT License
Classifier: Programming Language :: Python :: 3
Classifier: Programming Language :: Python :: 3.12
Classifier: Programming Language :: Python :: 3.13
Classifier: Topic :: Software Development :: Libraries :: Python Modules
Requires-Python: >=3.12
Requires-Dist: mcp>=1.2.0
Requires-Dist: pytest>=8.4.0
